setup.py
kbinstaller/__init__.py
kbinstaller.egg-info/PKG-INFO
kbinstaller.egg-info/SOURCES.txt
kbinstaller.egg-info/dependency_links.txt
kbinstaller.egg-info/top_level.txt