Metadata-Version: 1.0
Name: kbinstaller
Version: 1.0
Summary: Standalon installation Kivy Buildozer
Home-page: UNKNOWN
Author: UNKNOWN
Author-email: dankis12a@gmail.com
License: UNKNOWN
Platform: UNKNOWN
